README.md
cifar2png
setup.py
cifar2png.egg-info/PKG-INFO
cifar2png.egg-info/SOURCES.txt
cifar2png.egg-info/dependency_links.txt
cifar2png.egg-info/requires.txt
cifar2png.egg-info/top_level.txt
common/__init__.py
common/preprocess.py
common/spinner.py