Metadata-Version: 1.0
Name: cifar2png
Version: 0.0.4
Summary: Convert CIFAR-10 and CIFAR-100 datasets into PNG images
Home-page: https://github.com/knjcode/cifar2png
Author: Kenji Doi
Author-email: knjcode@gmail.com
License: MIT
Keywords: CIFAR-10 CIFAR-100 convert PNG
Platform: UNKNOWN
